[
  {
    "trend_arrow": "FLAT", 
    "display_time": "2016-10-26T14:58:33-07:00", 
    "noise": 1, 
    "system_time": "2016-10-26T21:56:16-07:00", 
    "direction": "Flat", 
    "sgv": 96, 
    "dateString": "2016-10-26T14:58:33-07:00", 
    "date": 1477519113000, 
    "unfiltered": 103952, 
    "filtered": 97088, 
    "device": "openaps://indy-e3/cgm", 
    "rssi": 682, 
    "type": "sgv", 
    "glucose": 96
  }, 
  {
    "trend_arrow": "NOT_COMPUTABLE", 
    "display_time": "2016-10-26T14:53:32-07:00", 
    "noise": 1, 
    "system_time": "2016-10-26T21:51:15-07:00", 
    "direction": "NOT COMPUTABLE", 
    "sgv": 90, 
    "dateString": "2016-10-26T14:53:32-07:00", 
    "date": 1477518812000, 
    "unfiltered": 97888, 
    "filtered": 94240, 
    "device": "openaps://indy-e3/cgm", 
    "rssi": 163, 
    "type": "sgv", 
    "glucose": 90
  }
]