[
  {
    "trend_arrow": "FLAT", 
    "display_time": "2016-11-17T07:22:14-08:00", 
    "noise": 1, 
    "system_time": "2016-11-17T15:21:45-08:00", 
    "direction": "Flat", 
    "sgv": 101, 
    "dateString": "2016-11-17T07:22:14-08:00", 
    "date": 1479396134000, 
    "unfiltered": 93440, 
    "filtered": 95504, 
    "device": "openaps://indy-e3/cgm", 
    "rssi": 185, 
    "type": "sgv", 
    "glucose": 101
  }, 
  {
    "trend_arrow": "FLAT", 
    "display_time": "2016-11-17T07:17:15-08:00", 
    "noise": 1, 
    "system_time": "2016-11-17T15:16:46-08:00", 
    "direction": "Flat", 
    "sgv": 104, 
    "dateString": "2016-11-17T07:17:15-08:00", 
    "date": 1479395835000, 
    "unfiltered": 95568, 
    "filtered": 97968, 
    "device": "openaps://indy-e3/cgm", 
    "rssi": 443, 
    "type": "sgv", 
    "glucose": 104
  }
]