[
  {
    "trend_arrow": "FLAT", 
    "display_time": "2016-09-03T11:50:50-07:00", 
    "noise": 1, 
    "system_time": "2016-09-03T18:49:20-07:00", 
    "direction": "Flat", 
    "sgv": 129, 
    "dateString": "2016-09-03T11:50:50-07:00", 
    "device": "openaps://cgm", 
    "unfiltered": 132704, 
    "rssi": 931, 
    "date": 1472928650000, 
    "filtered": 131072, 
    "type": "sgv", 
    "glucose": 129
  }, 
  {
    "trend_arrow": "FLAT", 
    "display_time": "2016-09-03T11:45:49-07:00", 
    "noise": 1, 
    "system_time": "2016-09-03T18:44:18-07:00", 
    "direction": "Flat", 
    "sgv": 129, 
    "dateString": "2016-09-03T11:45:49-07:00", 
    "device": "openaps://cgm", 
    "unfiltered": 132064, 
    "rssi": 160, 
    "date": 1472928349000, 
    "filtered": 130544, 
    "type": "sgv", 
    "glucose": 129
  }
]