[
  {
    "trend_arrow": "FLAT", 
    "display_time": "2016-10-25T01:13:38-07:00", 
    "noise": 1, 
    "system_time": "2016-10-25T08:11:21-07:00", 
    "direction": "Flat", 
    "sgv": 136, 
    "dateString": "2016-10-25T01:13:38-07:00", 
    "date": 1477383218000, 
    "unfiltered": 131808, 
    "filtered": 131840, 
    "device": "openaps://indy-e3/cgm", 
    "rssi": 196, 
    "type": "sgv", 
    "glucose": 136
  }, 
  {
    "trend_arrow": "FLAT", 
    "display_time": "2016-10-25T01:08:38-07:00", 
    "noise": 1, 
    "system_time": "2016-10-25T08:06:21-07:00", 
    "direction": "Flat", 
    "sgv": 136, 
    "dateString": "2016-10-25T01:08:38-07:00", 
    "date": 1477382918000, 
    "unfiltered": 132128, 
    "filtered": 132064, 
    "device": "openaps://indy-e3/cgm", 
    "rssi": 197, 
    "type": "sgv", 
    "glucose": 136
  }
]