[
  {
    "trend_arrow": "FLAT", 
    "display_time": "2016-09-11T04:31:16-07:00", 
    "noise": 1, 
    "system_time": "2016-09-11T11:29:46-07:00", 
    "direction": "Flat", 
    "sgv": 82, 
    "dateString": "2016-09-11T04:31:16-07:00", 
    "date": 1473593476000, 
    "unfiltered": 97744, 
    "filtered": 102080, 
    "device": "openaps://indy-e3/cgm", 
    "rssi": 184, 
    "type": "sgv", 
    "glucose": 82
  }, 
  {
    "trend_arrow": "FLAT", 
    "display_time": "2016-09-11T04:26:17-07:00", 
    "noise": 1, 
    "system_time": "2016-09-11T11:24:47-07:00", 
    "direction": "Flat", 
    "sgv": 85, 
    "dateString": "2016-09-11T04:26:17-07:00", 
    "date": 1473593177000, 
    "unfiltered": 101216, 
    "filtered": 106192, 
    "device": "openaps://indy-e3/cgm", 
    "rssi": 694, 
    "type": "sgv", 
    "glucose": 85
  }
]