[
  {
    "trend_arrow": "FLAT", 
    "display_time": "2016-09-08T22:21:25-07:00", 
    "noise": 1, 
    "system_time": "2016-09-09T05:19:54-07:00", 
    "direction": "Flat", 
    "sgv": 120, 
    "dateString": "2016-09-08T22:21:25-07:00", 
    "date": 1473398485000, 
    "unfiltered": 116864, 
    "filtered": 116928, 
    "device": "openaps://indy-e3/cgm", 
    "rssi": 187, 
    "type": "sgv", 
    "glucose": 120
  }, 
  {
    "trend_arrow": "FLAT", 
    "display_time": "2016-09-08T22:16:25-07:00", 
    "noise": 1, 
    "system_time": "2016-09-09T05:14:54-07:00", 
    "direction": "Flat", 
    "sgv": 119, 
    "dateString": "2016-09-08T22:16:25-07:00", 
    "date": 1473398185000, 
    "unfiltered": 116560, 
    "filtered": 117872, 
    "device": "openaps://indy-e3/cgm", 
    "rssi": 187, 
    "type": "sgv", 
    "glucose": 119
  }
]