[
  {
    "trend_arrow": "FLAT", 
    "display_time": "2016-11-07T02:01:13-08:00", 
    "noise": 1, 
    "system_time": "2016-11-07T10:00:45-08:00", 
    "direction": "Flat", 
    "sgv": 91, 
    "dateString": "2016-11-07T02:01:13-08:00", 
    "date": 1478512873000, 
    "unfiltered": 89104, 
    "filtered": 95232, 
    "device": "openaps://indy-e3/cgm", 
    "rssi": 195, 
    "type": "sgv", 
    "glucose": 91
  }, 
  {
    "trend_arrow": "FLAT", 
    "display_time": "2016-11-07T01:56:13-08:00", 
    "noise": 1, 
    "system_time": "2016-11-07T09:55:45-08:00", 
    "direction": "Flat", 
    "sgv": 95, 
    "dateString": "2016-11-07T01:56:13-08:00", 
    "date": 1478512573000, 
    "unfiltered": 92496, 
    "filtered": 97152, 
    "device": "openaps://indy-e3/cgm", 
    "rssi": 195, 
    "type": "sgv", 
    "glucose": 95
  }
]