[
  {
    "trend_arrow": "FLAT", 
    "display_time": "2016-11-03T20:16:21-07:00", 
    "noise": 1, 
    "system_time": "2016-11-04T03:15:54-07:00", 
    "direction": "Flat", 
    "sgv": 123, 
    "dateString": "2016-11-03T20:16:21-07:00", 
    "date": 1478229381000, 
    "unfiltered": 116048, 
    "filtered": 111984, 
    "device": "openaps://indy-e3/cgm", 
    "rssi": 165, 
    "type": "sgv", 
    "glucose": 123
  }, 
  {
    "trend_arrow": "45_UP", 
    "display_time": "2016-11-03T20:06:21-07:00", 
    "noise": 1, 
    "system_time": "2016-11-04T03:05:54-07:00", 
    "direction": "FortyFiveUp", 
    "sgv": 116, 
    "dateString": "2016-11-03T20:06:21-07:00", 
    "date": 1478228781000, 
    "unfiltered": 110736, 
    "filtered": 104592, 
    "device": "openaps://indy-e3/cgm", 
    "rssi": 162, 
    "type": "sgv", 
    "glucose": 116
  }
]