[
  {
    "trend_arrow": "45_DOWN", 
    "display_time": "2016-09-15T16:55:18-07:00", 
    "noise": 1, 
    "system_time": "2016-09-15T23:53:47-07:00", 
    "direction": "FortyFiveDown", 
    "sgv": 71, 
    "dateString": "2016-09-15T16:55:18-07:00", 
    "date": 1473983718000, 
    "unfiltered": 86064, 
    "filtered": 94928, 
    "device": "openaps://indy-e3/cgm", 
    "rssi": 164, 
    "type": "sgv", 
    "glucose": 71
  }, 
  {
    "trend_arrow": "SINGLE_DOWN", 
    "display_time": "2016-09-15T16:50:19-07:00", 
    "noise": 1, 
    "system_time": "2016-09-15T23:48:49-07:00", 
    "direction": "SingleDown", 
    "sgv": 78, 
    "dateString": "2016-09-15T16:50:19-07:00", 
    "date": 1473983419000, 
    "unfiltered": 91728, 
    "filtered": 103408, 
    "device": "openaps://indy-e3/cgm", 
    "rssi": 935, 
    "type": "sgv", 
    "glucose": 78
  }
]