[
  {
    "trend_arrow": "FLAT", 
    "display_time": "2016-11-02T03:36:26-07:00", 
    "noise": 1, 
    "system_time": "2016-11-02T10:35:59-07:00", 
    "direction": "Flat", 
    "sgv": 133, 
    "dateString": "2016-11-02T03:36:26-07:00", 
    "date": 1478082986000, 
    "unfiltered": 98240, 
    "filtered": 100432, 
    "device": "openaps://indy-e3/cgm", 
    "rssi": 187, 
    "type": "sgv", 
    "glucose": 133
  }, 
  {
    "trend_arrow": "FLAT", 
    "display_time": "2016-11-02T03:31:26-07:00", 
    "noise": 1, 
    "system_time": "2016-11-02T10:30:59-07:00", 
    "direction": "Flat", 
    "sgv": 135, 
    "dateString": "2016-11-02T03:31:26-07:00", 
    "date": 1478082686000, 
    "unfiltered": 99472, 
    "filtered": 98224, 
    "device": "openaps://indy-e3/cgm", 
    "rssi": 187, 
    "type": "sgv", 
    "glucose": 135
  }
]