[
  {
    "trend_arrow": "FLAT", 
    "display_time": "2016-11-13T06:20:58-08:00", 
    "noise": 1, 
    "system_time": "2016-11-13T14:20:29-08:00", 
    "direction": "Flat", 
    "sgv": 125, 
    "dateString": "2016-11-13T06:20:58-08:00", 
    "date": 1479046858000, 
    "unfiltered": 135072, 
    "filtered": 137568, 
    "device": "openaps://indy-e3/cgm", 
    "rssi": 191, 
    "type": "sgv", 
    "glucose": 125
  }, 
  {
    "trend_arrow": "FLAT", 
    "display_time": "2016-11-13T06:15:58-08:00", 
    "noise": 1, 
    "system_time": "2016-11-13T14:15:29-08:00", 
    "direction": "Flat", 
    "sgv": 127, 
    "dateString": "2016-11-13T06:15:58-08:00", 
    "date": 1479046558000, 
    "unfiltered": 136960, 
    "filtered": 139424, 
    "device": "openaps://indy-e3/cgm", 
    "rssi": 191, 
    "type": "sgv", 
    "glucose": 127
  }
]