[
  {
    "trend_arrow": "FLAT", 
    "display_time": "2016-11-03T22:06:21-07:00", 
    "noise": 1, 
    "system_time": "2016-11-04T05:05:54-07:00", 
    "direction": "Flat", 
    "sgv": 116, 
    "dateString": "2016-11-03T22:06:21-07:00", 
    "date": 1478235981000, 
    "unfiltered": 111312, 
    "filtered": 104848, 
    "device": "openaps://indy-e3/cgm", 
    "rssi": 419, 
    "type": "sgv", 
    "glucose": 116
  }, 
  {
    "trend_arrow": "FLAT", 
    "display_time": "2016-11-03T22:01:20-07:00", 
    "noise": 1, 
    "system_time": "2016-11-04T05:00:54-07:00", 
    "direction": "Flat", 
    "sgv": 109, 
    "dateString": "2016-11-03T22:01:20-07:00", 
    "date": 1478235680000, 
    "unfiltered": 105920, 
    "filtered": 106288, 
    "device": "openaps://indy-e3/cgm", 
    "rssi": 181, 
    "type": "sgv", 
    "glucose": 109
  }
]