[
  {
    "trend_arrow": "DOUBLE_DOWN", 
    "display_time": "2016-09-21T14:25:03-07:00", 
    "noise": 1, 
    "system_time": "2016-09-21T21:23:33-07:00", 
    "direction": "DoubleDown", 
    "sgv": 73, 
    "dateString": "2016-09-21T14:25:03-07:00", 
    "date": 1474493103000, 
    "unfiltered": 84112, 
    "filtered": 105152, 
    "device": "openaps://indy-e3/cgm", 
    "rssi": 186, 
    "type": "sgv", 
    "glucose": 73
  }, 
  {
    "trend_arrow": "SINGLE_DOWN", 
    "display_time": "2016-09-21T14:20:03-07:00", 
    "noise": 1, 
    "system_time": "2016-09-21T21:18:33-07:00", 
    "direction": "SingleDown", 
    "sgv": 89, 
    "dateString": "2016-09-21T14:20:03-07:00", 
    "date": 1474492803000, 
    "unfiltered": 97120, 
    "filtered": 117600, 
    "device": "openaps://indy-e3/cgm", 
    "rssi": 197, 
    "type": "sgv", 
    "glucose": 89
  }
]