[
  {
    "trend_arrow": "FLAT", 
    "display_time": "2016-11-07T06:06:15-08:00", 
    "noise": 1, 
    "system_time": "2016-11-07T14:05:47-08:00", 
    "direction": "Flat", 
    "sgv": 151, 
    "dateString": "2016-11-07T06:06:15-08:00", 
    "date": 1478527575000, 
    "unfiltered": 140224, 
    "filtered": 147104, 
    "device": "openaps://indy-e3/cgm", 
    "rssi": 449, 
    "type": "sgv", 
    "glucose": 151
  }, 
  {
    "trend_arrow": "FLAT", 
    "display_time": "2016-11-07T06:06:14-08:00", 
    "noise": 1, 
    "system_time": "2016-11-07T14:05:47-08:00", 
    "direction": "Flat", 
    "sgv": 151, 
    "dateString": "2016-11-07T06:06:14-08:00", 
    "date": 1478527574000, 
    "unfiltered": 145504, 
    "filtered": 147776, 
    "device": "openaps://indy-e3/cgm", 
    "rssi": 192, 
    "type": "sgv", 
    "glucose": 151
  }
]