[
  {
    "trend_arrow": "FLAT", 
    "display_time": "2016-11-05T03:11:17-07:00", 
    "noise": 1, 
    "system_time": "2016-11-05T10:10:51-07:00", 
    "direction": "Flat", 
    "sgv": 59, 
    "dateString": "2016-11-05T03:11:17-07:00", 
    "date": 1478340677000, 
    "unfiltered": 77088, 
    "filtered": 81072, 
    "device": "openaps://indy-e3/cgm", 
    "rssi": 179, 
    "type": "sgv", 
    "glucose": 59
  }, 
  {
    "trend_arrow": "FLAT", 
    "display_time": "2016-11-05T03:06:18-07:00", 
    "noise": 1, 
    "system_time": "2016-11-05T10:05:51-07:00", 
    "direction": "Flat", 
    "sgv": 62, 
    "dateString": "2016-11-05T03:06:18-07:00", 
    "date": 1478340378000, 
    "unfiltered": 79680, 
    "filtered": 84240, 
    "device": "openaps://indy-e3/cgm", 
    "rssi": 445, 
    "type": "sgv", 
    "glucose": 62
  }
]