[
  {
    "trend_arrow": "FLAT", 
    "display_time": "2016-11-20T15:42:02-08:00", 
    "noise": 1, 
    "direction": "Flat", 
    "system_time": "2016-11-20T23:41:32-08:00", 
    "sgv": 130, 
    "dateString": "2016-11-20T15:42:02-08:00", 
    "device": "openaps://indy-e3/cgm", 
    "unfiltered": 148160, 
    "rssi": 187, 
    "date": 1479685322000.0, 
    "filtered": 151936, 
    "type": "sgv", 
    "glucose": 130
  }, 
  {
    "trend_arrow": "FLAT", 
    "display_time": "2016-11-20T15:37:02-08:00", 
    "noise": 1, 
    "direction": "Flat", 
    "system_time": "2016-11-20T23:36:32-08:00", 
    "sgv": 133, 
    "dateString": "2016-11-20T15:37:02-08:00", 
    "device": "openaps://indy-e3/cgm", 
    "unfiltered": 151008, 
    "rssi": 185, 
    "date": 1479685022000.0, 
    "filtered": 155488, 
    "type": "sgv", 
    "glucose": 133
  }, 
  {
    "trend_arrow": "FLAT", 
    "display_time": "2016-11-20T15:32:02-08:00", 
    "noise": 1, 
    "direction": "Flat", 
    "system_time": "2016-11-20T23:31:33-08:00", 
    "sgv": 137, 
    "dateString": "2016-11-20T15:32:02-08:00", 
    "device": "openaps://indy-e3/cgm", 
    "unfiltered": 154176, 
    "rssi": 185, 
    "date": 1479684722000.0, 
    "filtered": 160000, 
    "type": "sgv", 
    "glucose": 137
  }, 
  {
    "trend_arrow": "45_DOWN", 
    "display_time": "2016-11-20T15:27:02-08:00", 
    "noise": 1, 
    "direction": "FortyFiveDown", 
    "system_time": "2016-11-20T23:26:32-08:00", 
    "sgv": 139, 
    "dateString": "2016-11-20T15:27:02-08:00", 
    "device": "openaps://indy-e3/cgm", 
    "unfiltered": 156416, 
    "rssi": 187, 
    "date": 1479684422000.0, 
    "filtered": 164736, 
    "type": "sgv", 
    "glucose": 139
  }, 
  {
    "trend_arrow": "FLAT", 
    "display_time": "2016-11-20T15:22:02-08:00", 
    "noise": 1, 
    "direction": "Flat", 
    "system_time": "2016-11-20T23:21:33-08:00", 
    "sgv": 145, 
    "dateString": "2016-11-20T15:22:02-08:00", 
    "device": "openaps://indy-e3/cgm", 
    "unfiltered": 161536, 
    "rssi": 179, 
    "date": 1479684122000.0, 
    "filtered": 168640, 
    "type": "sgv", 
    "glucose": 145
  }, 
  {
    "trend_arrow": "FLAT", 
    "display_time": "2016-11-20T15:22:02-08:00", 
    "noise": 1, 
    "direction": "Flat", 
    "system_time": "2016-11-20T23:21:33-08:00", 
    "sgv": 139, 
    "dateString": "2016-11-20T15:22:02-08:00", 
    "device": "openaps://indy-e3/cgm", 
    "unfiltered": 166752, 
    "rssi": 207, 
    "date": 1479684122000.0, 
    "filtered": 171136, 
    "type": "sgv", 
    "glucose": 139
  }, 
  {
    "trend_arrow": "NOT_COMPUTABLE", 
    "display_time": "2016-11-20T15:17:02-08:00", 
    "noise": 1, 
    "direction": "NOT COMPUTABLE", 
    "system_time": "2016-11-20T23:16:32-08:00", 
    "sgv": 5, 
    "dateString": "2016-11-20T15:17:02-08:00", 
    "device": "openaps://indy-e3/cgm", 
    "date": 1479683822000.0, 
    "type": "sgv", 
    "glucose": 5
  }
]