[
  {
    "trend_arrow": "FLAT", 
    "display_time": "2016-11-19T11:47:06-08:00", 
    "noise": 1, 
    "system_time": "2016-11-19T19:46:37-08:00", 
    "direction": "Flat", 
    "sgv": 93, 
    "dateString": "2016-11-19T11:47:06-08:00", 
    "device": "openaps://indy-e3/cgm", 
    "unfiltered": 94800, 
    "rssi": 163, 
    "date": 1479584826000, 
    "filtered": 92512, 
    "type": "sgv", 
    "glucose": 93
  }, 
  {
    "trend_arrow": "FLAT", 
    "display_time": "2016-11-19T11:42:06-08:00", 
    "noise": 1, 
    "system_time": "2016-11-19T19:41:37-08:00", 
    "direction": "Flat", 
    "sgv": 90, 
    "dateString": "2016-11-19T11:42:06-08:00", 
    "device": "openaps://indy-e3/cgm", 
    "unfiltered": 92464, 
    "rssi": 168, 
    "date": 1479584526000, 
    "filtered": 92544, 
    "type": "sgv", 
    "glucose": 90
  }
]