[
  {
    "trend_arrow": "FLAT", 
    "display_time": "2016-10-31T02:03:18-07:00", 
    "noise": 1, 
    "system_time": "2016-10-31T09:02:52-07:00", 
    "direction": "Flat", 
    "sgv": 78, 
    "dateString": "2016-10-31T02:03:18-07:00", 
    "device": "openaps://indy-e3/cgm", 
    "unfiltered": 81312, 
    "rssi": 185, 
    "date": 1477904598000, 
    "filtered": 83008, 
    "type": "sgv", 
    "glucose": 78
  }, 
  {
    "trend_arrow": "FLAT", 
    "display_time": "2016-10-31T01:58:18-07:00", 
    "noise": 1, 
    "system_time": "2016-10-31T08:57:52-07:00", 
    "direction": "Flat", 
    "sgv": 80, 
    "dateString": "2016-10-31T01:58:18-07:00", 
    "device": "openaps://indy-e3/cgm", 
    "unfiltered": 82384, 
    "rssi": 185, 
    "date": 1477904298000, 
    "filtered": 83376, 
    "type": "sgv", 
    "glucose": 80
  }
]