[
  {
    "trend_arrow": "45_UP", 
    "display_time": "2016-10-19T21:38:57-07:00", 
    "noise": 1, 
    "direction": "FortyFiveUp", 
    "system_time": "2016-10-20T04:36:41-07:00", 
    "sgv": 182, 
    "dateString": "2016-10-19T21:38:57-07:00", 
    "device": "openaps://indy-e3/cgm", 
    "unfiltered": 155936, 
    "rssi": 185, 
    "date": 1476938337000.0, 
    "filtered": 151168, 
    "type": "sgv", 
    "glucose": 182
  }, 
  {
    "trend_arrow": "45_UP", 
    "display_time": "2016-10-19T21:33:57-07:00", 
    "noise": 1, 
    "direction": "FortyFiveUp", 
    "system_time": "2016-10-20T04:31:41-07:00", 
    "sgv": 177, 
    "dateString": "2016-10-19T21:33:57-07:00", 
    "device": "openaps://indy-e3/cgm", 
    "unfiltered": 152672, 
    "rssi": 194, 
    "date": 1476938037000.0, 
    "filtered": 147168, 
    "type": "sgv", 
    "glucose": 177
  }, 
  {
    "trend_arrow": "45_UP", 
    "display_time": "2016-10-19T21:28:58-07:00", 
    "noise": 1, 
    "direction": "FortyFiveUp", 
    "system_time": "2016-10-20T04:26:43-07:00", 
    "sgv": 174, 
    "dateString": "2016-10-19T21:28:58-07:00", 
    "device": "openaps://indy-e3/cgm", 
    "unfiltered": 150272, 
    "rssi": 172, 
    "date": 1476937738000.0, 
    "filtered": 143168, 
    "type": "sgv", 
    "glucose": 174
  }, 
  {
    "trend_arrow": "45_UP", 
    "display_time": "2016-10-19T21:28:58-07:00", 
    "noise": 1, 
    "direction": "FortyFiveUp", 
    "system_time": "2016-10-20T04:26:43-07:00", 
    "sgv": 181, 
    "dateString": "2016-10-19T21:28:58-07:00", 
    "device": "openaps://indy-e3/cgm", 
    "unfiltered": 145696, 
    "rssi": 180, 
    "date": 1476937738000.0, 
    "filtered": 139808, 
    "type": "sgv", 
    "glucose": 181
  }, 
  {
    "trend_arrow": "FLAT", 
    "display_time": "2016-10-19T21:23:57-07:00", 
    "noise": 1, 
    "direction": "Flat", 
    "system_time": "2016-10-20T04:21:41-07:00", 
    "sgv": 159, 
    "dateString": "2016-10-19T21:23:57-07:00", 
    "device": "openaps://indy-e3/cgm", 
    "unfiltered": 141344, 
    "rssi": 180, 
    "date": 1476937437000.0, 
    "filtered": 137376, 
    "type": "sgv", 
    "glucose": 159
  }, 
  {
    "trend_arrow": "FLAT", 
    "display_time": "2016-10-19T21:18:57-07:00", 
    "noise": 1, 
    "direction": "Flat", 
    "system_time": "2016-10-20T04:16:41-07:00", 
    "sgv": 152, 
    "dateString": "2016-10-19T21:18:57-07:00", 
    "device": "openaps://indy-e3/cgm", 
    "unfiltered": 138304, 
    "rssi": 186, 
    "date": 1476937137000.0, 
    "filtered": 135680, 
    "type": "sgv", 
    "glucose": 152
  }, 
  {
    "trend_arrow": "FLAT", 
    "display_time": "2016-10-19T21:13:57-07:00", 
    "noise": 1, 
    "direction": "Flat", 
    "system_time": "2016-10-20T04:11:41-07:00", 
    "sgv": 148, 
    "dateString": "2016-10-19T21:13:57-07:00", 
    "device": "openaps://indy-e3/cgm", 
    "date": 1476936837000.0, 
    "type": "sgv", 
    "glucose": 148
  }
]