[
  {
    "trend_arrow": "FLAT", 
    "display_time": "2016-11-13T06:40:58-08:00", 
    "noise": 1, 
    "system_time": "2016-11-13T14:40:29-08:00", 
    "direction": "Flat", 
    "sgv": 117, 
    "dateString": "2016-11-13T06:40:58-08:00", 
    "device": "openaps://indy-e3/cgm", 
    "unfiltered": 127376, 
    "rssi": 191, 
    "date": 1479048058000, 
    "filtered": 130400, 
    "type": "sgv", 
    "glucose": 117
  }, 
  {
    "trend_arrow": "FLAT", 
    "display_time": "2016-11-13T06:35:58-08:00", 
    "noise": 1, 
    "system_time": "2016-11-13T14:35:29-08:00", 
    "direction": "Flat", 
    "sgv": 119, 
    "dateString": "2016-11-13T06:35:58-08:00", 
    "device": "openaps://indy-e3/cgm", 
    "unfiltered": 129248, 
    "rssi": 191, 
    "date": 1479047758000, 
    "filtered": 132384, 
    "type": "sgv", 
    "glucose": 119
  }
]