[
  {
    "trend_arrow": "FLAT", 
    "system_time": "2016-09-24T20:33:25", 
    "noise": 1, 
    "direction": "Flat", 
    "sgv": 124, 
    "display_time": "2016-09-24T13:34:56", 
    "date": 1474749296000.0, 
    "dateString": "2016-09-24T13:34:56", 
    "unfiltered": 129200, 
    "filtered": 137056, 
    "device": "openaps://indy-e3/cgm", 
    "rssi": 163, 
    "type": "sgv", 
    "glucose": 124
  }, 
  {
    "trend_arrow": "FLAT", 
    "system_time": "2016-09-24T20:28:25", 
    "noise": 1, 
    "direction": "Flat", 
    "sgv": 128, 
    "display_time": "2016-09-24T13:29:56", 
    "date": 1474748996000.0, 
    "dateString": "2016-09-24T13:29:56", 
    "unfiltered": 132960, 
    "filtered": 141056, 
    "device": "openaps://indy-e3/cgm", 
    "rssi": 163, 
    "type": "sgv", 
    "glucose": 128
  }, 
  {
    "trend_arrow": "FLAT", 
    "system_time": "2016-09-24T20:23:25", 
    "noise": 1, 
    "direction": "Flat", 
    "sgv": 135, 
    "display_time": "2016-09-24T13:24:56", 
    "date": 1474748696000.0, 
    "dateString": "2016-09-24T13:24:56", 
    "unfiltered": 139424, 
    "filtered": 143648, 
    "device": "openaps://indy-e3/cgm", 
    "rssi": 166, 
    "type": "sgv", 
    "glucose": 135
  }, 
  {
    "trend_arrow": "FLAT", 
    "system_time": "2016-09-24T20:13:25", 
    "noise": 1, 
    "direction": "Flat", 
    "sgv": 141, 
    "display_time": "2016-09-24T13:14:56", 
    "date": 1474748096000.0, 
    "dateString": "2016-09-24T13:14:56", 
    "unfiltered": 145120, 
    "filtered": 146816, 
    "device": "openaps://indy-e3/cgm", 
    "rssi": 166, 
    "type": "sgv", 
    "glucose": 141
  }, 
  {
    "trend_arrow": "FLAT", 
    "system_time": "2016-09-24T20:08:26", 
    "noise": 1, 
    "direction": "Flat", 
    "sgv": 142, 
    "display_time": "2016-09-24T13:09:56", 
    "date": 1474747796000.0, 
    "dateString": "2016-09-24T13:09:56", 
    "unfiltered": 145760, 
    "filtered": 149024, 
    "device": "openaps://indy-e3/cgm", 
    "rssi": 414, 
    "type": "sgv", 
    "glucose": 142
  }
]