[
  {
    "trend_arrow": "FLAT", 
    "system_time": "2016-09-29T05:38:33", 
    "noise": 1, 
    "direction": "Flat", 
    "sgv": 229, 
    "display_time": "2016-09-28T22:40:03", 
    "date": 1475127603000.0, 
    "dateString": "2016-09-28T22:40:03", 
    "unfiltered": 205120, 
    "filtered": 204416, 
    "device": "openaps://indy-e3/cgm", 
    "rssi": 193, 
    "type": "sgv", 
    "glucose": 229
  }, 
  {
    "trend_arrow": "45_UP", 
    "system_time": "2016-09-29T05:33:33", 
    "noise": 1, 
    "direction": "FortyFiveUp", 
    "sgv": 224, 
    "display_time": "2016-09-28T22:35:04", 
    "date": 1475127304000.0, 
    "dateString": "2016-09-28T22:35:04", 
    "unfiltered": 201472, 
    "filtered": 198848, 
    "device": "openaps://indy-e3/cgm", 
    "rssi": 194, 
    "type": "sgv", 
    "glucose": 224
  }, 
  {
    "trend_arrow": "SINGLE_UP", 
    "system_time": "2016-09-29T05:28:33", 
    "noise": 1, 
    "direction": "SingleUp", 
    "sgv": 229, 
    "display_time": "2016-09-28T22:30:03", 
    "date": 1475127003000.0, 
    "dateString": "2016-09-28T22:30:03", 
    "unfiltered": 204960, 
    "filtered": 190496, 
    "device": "openaps://indy-e3/cgm", 
    "rssi": 186, 
    "type": "sgv", 
    "glucose": 229
  }, 
  {
    "trend_arrow": "SINGLE_UP", 
    "system_time": "2016-09-29T05:23:33", 
    "noise": 1, 
    "direction": "SingleUp", 
    "sgv": 221, 
    "display_time": "2016-09-28T22:25:03", 
    "date": 1475126703000.0, 
    "dateString": "2016-09-28T22:25:03", 
    "unfiltered": 199104, 
    "filtered": 182048, 
    "device": "openaps://indy-e3/cgm", 
    "rssi": 179, 
    "type": "sgv", 
    "glucose": 221
  }, 
  {
    "trend_arrow": "45_UP", 
    "system_time": "2016-09-29T05:18:33", 
    "noise": 1, 
    "direction": "FortyFiveUp", 
    "sgv": 202, 
    "display_time": "2016-09-28T22:20:03", 
    "date": 1475126403000.0, 
    "dateString": "2016-09-28T22:20:03", 
    "unfiltered": 185152, 
    "filtered": 175648, 
    "device": "openaps://indy-e3/cgm", 
    "rssi": 180, 
    "type": "sgv", 
    "glucose": 202
  }, 
  {
    "trend_arrow": "45_UP", 
    "system_time": "2016-09-29T05:13:33", 
    "noise": 1, 
    "direction": "FortyFiveUp", 
    "sgv": 193, 
    "display_time": "2016-09-28T22:15:03", 
    "date": 1475126103000.0, 
    "dateString": "2016-09-28T22:15:03", 
    "unfiltered": 178176, 
    "filtered": 170880, 
    "device": "openaps://indy-e3/cgm", 
    "rssi": 192, 
    "type": "sgv", 
    "glucose": 193
  }
]