[
  {
    "trend_arrow": "45_DOWN", 
    "display_time": "2016-09-09T03:06:24-07:00", 
    "noise": 1, 
    "direction": "FortyFiveDown", 
    "system_time": "2016-09-09T10:04:54-07:00", 
    "sgv": 143, 
    "dateString": "2016-09-09T03:06:24-07:00", 
    "device": "openaps://indy-e3/cgm", 
    "unfiltered": 137344, 
    "rssi": 186, 
    "date": 1473415584000.0, 
    "filtered": 144256, 
    "type": "sgv", 
    "glucose": 143
  }, 
  {
    "trend_arrow": "45_DOWN", 
    "display_time": "2016-09-09T03:01:24-07:00", 
    "noise": 1, 
    "direction": "FortyFiveDown", 
    "system_time": "2016-09-09T09:59:54-07:00", 
    "sgv": 149, 
    "dateString": "2016-09-09T03:01:24-07:00", 
    "device": "openaps://indy-e3/cgm", 
    "unfiltered": 141568, 
    "rssi": 188, 
    "date": 1473415284000.0, 
    "filtered": 148864, 
    "type": "sgv", 
    "glucose": 149
  }, 
  {
    "trend_arrow": "FLAT", 
    "display_time": "2016-09-09T02:56:25-07:00", 
    "noise": 1, 
    "direction": "Flat", 
    "system_time": "2016-09-09T09:54:54-07:00", 
    "sgv": 155, 
    "dateString": "2016-09-09T02:56:25-07:00", 
    "device": "openaps://indy-e3/cgm", 
    "unfiltered": 146112, 
    "rssi": 429, 
    "date": 1473414985000.0, 
    "filtered": 152928, 
    "type": "sgv", 
    "glucose": 155
  }, 
  {
    "trend_arrow": "FLAT", 
    "display_time": "2016-09-09T02:51:24-07:00", 
    "noise": 1, 
    "direction": "Flat", 
    "system_time": "2016-09-09T09:49:54-07:00", 
    "sgv": 161, 
    "dateString": "2016-09-09T02:51:24-07:00", 
    "device": "openaps://indy-e3/cgm", 
    "unfiltered": 150720, 
    "rssi": 187, 
    "date": 1473414684000.0, 
    "filtered": 156192, 
    "type": "sgv", 
    "glucose": 161
  }, 
  {
    "trend_arrow": "FLAT", 
    "display_time": "2016-09-09T02:46:24-07:00", 
    "noise": 1, 
    "direction": "Flat", 
    "system_time": "2016-09-09T09:44:54-07:00", 
    "sgv": 167, 
    "dateString": "2016-09-09T02:46:24-07:00", 
    "device": "openaps://indy-e3/cgm", 
    "unfiltered": 154848, 
    "rssi": 187, 
    "date": 1473414384000.0, 
    "filtered": 158560, 
    "type": "sgv", 
    "glucose": 167
  }, 
  {
    "trend_arrow": "FLAT", 
    "display_time": "2016-09-09T02:41:24-07:00", 
    "noise": 1, 
    "direction": "Flat", 
    "system_time": "2016-09-09T09:39:54-07:00", 
    "sgv": 170, 
    "dateString": "2016-09-09T02:41:24-07:00", 
    "device": "openaps://indy-e3/cgm", 
    "unfiltered": 157568, 
    "rssi": 196, 
    "date": 1473414084000.0, 
    "filtered": 160064, 
    "type": "sgv", 
    "glucose": 170
  }
]