[
  {
    "trend_arrow": "FLAT", 
    "display_time": "2016-09-21T04:05:04-07:00", 
    "noise": 1, 
    "direction": "Flat", 
    "system_time": "2016-09-21T11:03:34-07:00", 
    "sgv": 125, 
    "dateString": "2016-09-21T04:05:04-07:00", 
    "device": "openaps://indy-e3/cgm", 
    "unfiltered": 130128, 
    "rssi": 189, 
    "date": 1474455904000.0, 
    "filtered": 123296, 
    "type": "sgv", 
    "glucose": 125
  }, 
  {
    "trend_arrow": "FLAT", 
    "display_time": "2016-09-21T04:00:04-07:00", 
    "noise": 1, 
    "direction": "Flat", 
    "system_time": "2016-09-21T10:58:34-07:00", 
    "sgv": 117, 
    "dateString": "2016-09-21T04:00:04-07:00", 
    "device": "openaps://indy-e3/cgm", 
    "unfiltered": 124528, 
    "rssi": 189, 
    "date": 1474455604000.0, 
    "filtered": 122000, 
    "type": "sgv", 
    "glucose": 117
  }, 
  {
    "trend_arrow": "FLAT", 
    "display_time": "2016-09-21T03:55:04-07:00", 
    "noise": 1, 
    "direction": "Flat", 
    "system_time": "2016-09-21T10:53:34-07:00", 
    "sgv": 113, 
    "dateString": "2016-09-21T03:55:04-07:00", 
    "device": "openaps://indy-e3/cgm", 
    "unfiltered": 121520, 
    "rssi": 186, 
    "date": 1474455304000.0, 
    "filtered": 121856, 
    "type": "sgv", 
    "glucose": 113
  }, 
  {
    "trend_arrow": "FLAT", 
    "display_time": "2016-09-21T03:50:04-07:00", 
    "noise": 1, 
    "direction": "Flat", 
    "system_time": "2016-09-21T10:48:34-07:00", 
    "sgv": 114, 
    "dateString": "2016-09-21T03:50:04-07:00", 
    "device": "openaps://indy-e3/cgm", 
    "unfiltered": 121984, 
    "rssi": 177, 
    "date": 1474455004000.0, 
    "filtered": 121536, 
    "type": "sgv", 
    "glucose": 114
  }, 
  {
    "trend_arrow": "FLAT", 
    "display_time": "2016-09-21T03:45:04-07:00", 
    "noise": 1, 
    "direction": "Flat", 
    "system_time": "2016-09-21T10:43:34-07:00", 
    "sgv": 112, 
    "dateString": "2016-09-21T03:45:04-07:00", 
    "device": "openaps://indy-e3/cgm", 
    "unfiltered": 120672, 
    "rssi": 177, 
    "date": 1474454704000.0, 
    "filtered": 120192, 
    "type": "sgv", 
    "glucose": 112
  }, 
  {
    "trend_arrow": "FLAT", 
    "display_time": "2016-09-21T03:40:04-07:00", 
    "noise": 1, 
    "direction": "Flat", 
    "system_time": "2016-09-21T10:38:34-07:00", 
    "sgv": 113, 
    "dateString": "2016-09-21T03:40:04-07:00", 
    "device": "openaps://indy-e3/cgm", 
    "unfiltered": 121152, 
    "rssi": 176, 
    "date": 1474454404000.0, 
    "filtered": 117952, 
    "type": "sgv", 
    "glucose": 113
  }
]