[
  {
    "trend_arrow": "FLAT", 
    "system_time": "2016-11-23T14:56:23", 
    "noise": 1, 
    "direction": "Flat", 
    "sgv": 98, 
    "display_time": "2016-11-23T06:56:53", 
    "date": 1479913013000.0, 
    "dateString": "2016-11-23T06:56:53", 
    "unfiltered": 111376, 
    "filtered": 116784, 
    "device": "openaps://indy-e3/cgm", 
    "rssi": 432, 
    "type": "sgv", 
    "glucose": 98
  }, 
  {
    "trend_arrow": "FLAT", 
    "system_time": "2016-11-23T14:51:23", 
    "noise": 1, 
    "direction": "Flat", 
    "sgv": 102, 
    "display_time": "2016-11-23T06:51:52", 
    "date": 1479912712000.0, 
    "dateString": "2016-11-23T06:51:52", 
    "unfiltered": 114672, 
    "filtered": 119328, 
    "device": "openaps://indy-e3/cgm", 
    "rssi": 182, 
    "type": "sgv", 
    "glucose": 102
  }, 
  {
    "trend_arrow": "FLAT", 
    "system_time": "2016-11-23T14:46:23", 
    "noise": 1, 
    "direction": "Flat", 
    "sgv": 106, 
    "display_time": "2016-11-23T06:46:53", 
    "date": 1479912413000.0, 
    "dateString": "2016-11-23T06:46:53", 
    "unfiltered": 118016, 
    "filtered": 121344, 
    "device": "openaps://indy-e3/cgm", 
    "rssi": 437, 
    "type": "sgv", 
    "glucose": 106
  }, 
  {
    "trend_arrow": "FLAT", 
    "system_time": "2016-11-23T14:41:23", 
    "noise": 1, 
    "direction": "Flat", 
    "sgv": 110, 
    "display_time": "2016-11-23T06:41:52", 
    "date": 1479912112000.0, 
    "dateString": "2016-11-23T06:41:52", 
    "unfiltered": 121360, 
    "filtered": 123504, 
    "device": "openaps://indy-e3/cgm", 
    "rssi": 177, 
    "type": "sgv", 
    "glucose": 110
  }, 
  {
    "trend_arrow": "FLAT", 
    "system_time": "2016-11-23T14:36:23", 
    "noise": 1, 
    "direction": "Flat", 
    "sgv": 112, 
    "display_time": "2016-11-23T06:36:52", 
    "date": 1479911812000.0, 
    "dateString": "2016-11-23T06:36:52", 
    "unfiltered": 122640, 
    "filtered": 126304, 
    "device": "openaps://indy-e3/cgm", 
    "rssi": 190, 
    "type": "sgv", 
    "glucose": 112
  }, 
  {
    "trend_arrow": "FLAT", 
    "system_time": "2016-11-23T14:31:23", 
    "noise": 1, 
    "direction": "Flat", 
    "sgv": 113, 
    "display_time": "2016-11-23T06:31:52", 
    "date": 1479911512000.0, 
    "dateString": "2016-11-23T06:31:52", 
    "unfiltered": 123760, 
    "filtered": 129936, 
    "device": "openaps://indy-e3/cgm", 
    "rssi": 186, 
    "type": "sgv", 
    "glucose": 113
  }
]