[
  {
    "trend_arrow": "NOT_COMPUTABLE", 
    "display_time": "2016-10-30T08:58:21-07:00", 
    "noise": 4, 
    "system_time": "2016-10-30T15:57:56-07:00", 
    "direction": "NOT COMPUTABLE", 
    "sgv": 10, 
    "dateString": "2016-10-30T08:58:21-07:00", 
    "device": "openaps://indy-e3/cgm", 
    "unfiltered": 148960, 
    "rssi": 674, 
    "date": 1477843101000, 
    "filtered": 116848, 
    "type": "sgv", 
    "glucose": 10
  }, 
  {
    "trend_arrow": "NOT_COMPUTABLE", 
    "display_time": "2016-10-30T08:53:20-07:00", 
    "noise": 3, 
    "system_time": "2016-10-30T15:52:55-07:00", 
    "direction": "NOT COMPUTABLE", 
    "sgv": 114, 
    "dateString": "2016-10-30T08:53:20-07:00", 
    "device": "openaps://indy-e3/cgm", 
    "unfiltered": 110560, 
    "rssi": 167, 
    "date": 1477842800000, 
    "filtered": 122240, 
    "type": "sgv", 
    "glucose": 114
  }
]