[
  {
    "trend_arrow": "FLAT", 
    "display_time": "2016-11-01T03:23:14-07:00", 
    "noise": 1, 
    "system_time": "2016-11-01T10:22:48-07:00", 
    "direction": "Flat", 
    "sgv": 151, 
    "dateString": "2016-11-01T03:23:14-07:00", 
    "device": "openaps://indy-e3/cgm", 
    "unfiltered": 130064, 
    "rssi": 183, 
    "date": 1477995794000, 
    "filtered": 131392, 
    "type": "sgv", 
    "glucose": 151
  }, 
  {
    "trend_arrow": "FLAT", 
    "display_time": "2016-11-01T03:18:14-07:00", 
    "noise": 1, 
    "system_time": "2016-11-01T10:17:48-07:00", 
    "direction": "Flat", 
    "sgv": 151, 
    "dateString": "2016-11-01T03:18:14-07:00", 
    "device": "openaps://indy-e3/cgm", 
    "unfiltered": 130496, 
    "rssi": 183, 
    "date": 1477995494000, 
    "filtered": 132128, 
    "type": "sgv", 
    "glucose": 151
  }
]