[
  {
    "trend_arrow": "NOT_COMPUTABLE", 
    "display_time": "2016-09-27T17:15:09-07:00", 
    "noise": 1, 
    "system_time": "2016-09-28T00:13:39-07:00", 
    "direction": "NOT COMPUTABLE", 
    "sgv": 59, 
    "dateString": "2016-09-27T17:15:09-07:00", 
    "device": "openaps://indy-e3/cgm", 
    "unfiltered": 86256, 
    "rssi": 673, 
    "date": 1475021709000, 
    "filtered": 95952, 
    "type": "sgv", 
    "glucose": 59
  }, 
  {
    "trend_arrow": "NOT_COMPUTABLE", 
    "display_time": "2016-09-27T17:00:09-07:00", 
    "noise": 1, 
    "system_time": "2016-09-27T23:58:38-07:00", 
    "direction": "NOT COMPUTABLE", 
    "sgv": 83, 
    "dateString": "2016-09-27T17:00:09-07:00", 
    "device": "openaps://indy-e3/cgm", 
    "unfiltered": 103600, 
    "rssi": 415, 
    "date": 1475020809000, 
    "filtered": 109136, 
    "type": "sgv", 
    "glucose": 83
  }
]