[
  {
    "trend_arrow": "FLAT", 
    "display_time": "2016-09-10T21:46:18-07:00", 
    "noise": 1, 
    "system_time": "2016-09-11T04:44:47-07:00", 
    "direction": "Flat", 
    "sgv": 79, 
    "dateString": "2016-09-10T21:46:18-07:00", 
    "device": "openaps://indy-e3/cgm", 
    "unfiltered": 92912, 
    "rssi": 440, 
    "date": 1473569178000, 
    "filtered": 91088, 
    "type": "sgv", 
    "glucose": 79
  }, 
  {
    "trend_arrow": "NOT_COMPUTABLE", 
    "display_time": "2016-09-10T21:41:17-07:00", 
    "noise": 1, 
    "system_time": "2016-09-11T04:39:47-07:00", 
    "direction": "NOT COMPUTABLE", 
    "sgv": 80, 
    "dateString": "2016-09-10T21:41:17-07:00", 
    "device": "openaps://indy-e3/cgm", 
    "unfiltered": 93744, 
    "rssi": 186, 
    "date": 1473568877000, 
    "filtered": 91712, 
    "type": "sgv", 
    "glucose": 80
  }
]