[
  {
    "trend_arrow": "FLAT", 
    "display_time": "2016-11-08T16:41:10-08:00", 
    "noise": 1, 
    "direction": "Flat", 
    "system_time": "2016-11-09T00:40:41-08:00", 
    "sgv": 86, 
    "dateString": "2016-11-08T16:41:10-08:00", 
    "device": "openaps://indy-e3/cgm", 
    "unfiltered": 80080, 
    "rssi": 188, 
    "date": 1478652070000.0, 
    "filtered": 79648, 
    "type": "sgv", 
    "glucose": 86
  }, 
  {
    "trend_arrow": "FLAT", 
    "display_time": "2016-11-08T16:36:10-08:00", 
    "noise": 1, 
    "direction": "Flat", 
    "system_time": "2016-11-09T00:35:41-08:00", 
    "sgv": 83, 
    "dateString": "2016-11-08T16:36:10-08:00", 
    "device": "openaps://indy-e3/cgm", 
    "unfiltered": 78032, 
    "rssi": 190, 
    "date": 1478651770000.0, 
    "filtered": 80688, 
    "type": "sgv", 
    "glucose": 83
  }, 
  {
    "trend_arrow": "FLAT", 
    "display_time": "2016-11-08T16:31:10-08:00", 
    "noise": 1, 
    "direction": "Flat", 
    "system_time": "2016-11-09T00:30:41-08:00", 
    "sgv": 85, 
    "dateString": "2016-11-08T16:31:10-08:00", 
    "device": "openaps://indy-e3/cgm", 
    "unfiltered": 79504, 
    "rssi": 196, 
    "date": 1478651470000.0, 
    "filtered": 81152, 
    "type": "sgv", 
    "glucose": 85
  }, 
  {
    "trend_arrow": "FLAT", 
    "display_time": "2016-11-08T16:26:10-08:00", 
    "noise": 1, 
    "direction": "Flat", 
    "system_time": "2016-11-09T00:25:41-08:00", 
    "sgv": 87, 
    "dateString": "2016-11-08T16:26:10-08:00", 
    "device": "openaps://indy-e3/cgm", 
    "unfiltered": 81152, 
    "rssi": 181, 
    "date": 1478651170000.0, 
    "filtered": 80288, 
    "type": "sgv", 
    "glucose": 87
  }, 
  {
    "trend_arrow": "FLAT", 
    "display_time": "2016-11-08T16:21:09-08:00", 
    "noise": 1, 
    "direction": "Flat", 
    "system_time": "2016-11-09T00:20:41-08:00", 
    "sgv": 87, 
    "dateString": "2016-11-08T16:21:09-08:00", 
    "device": "openaps://indy-e3/cgm", 
    "unfiltered": 80912, 
    "rssi": 177, 
    "date": 1478650869000.0, 
    "filtered": 78048, 
    "type": "sgv", 
    "glucose": 87
  }, 
  {
    "trend_arrow": "FLAT", 
    "display_time": "2016-11-08T16:16:09-08:00", 
    "noise": 1, 
    "direction": "Flat", 
    "system_time": "2016-11-09T00:15:41-08:00", 
    "sgv": 85, 
    "dateString": "2016-11-08T16:16:09-08:00", 
    "device": "openaps://indy-e3/cgm", 
    "unfiltered": 79248, 
    "rssi": 199, 
    "date": 1478650569000.0, 
    "filtered": 74960, 
    "type": "sgv", 
    "glucose": 85
  }
]