[
  {
    "trend_arrow": "FLAT", 
    "display_time": "2016-10-14T16:04:15-07:00", 
    "noise": 1, 
    "system_time": "2016-10-14T23:02:29-07:00", 
    "direction": "Flat", 
    "sgv": 70, 
    "dateString": "2016-10-14T16:04:15-07:00", 
    "device": "openaps://indy-e3/cgm", 
    "unfiltered": 77408, 
    "rssi": 183, 
    "date": 1476486255000, 
    "filtered": 81744, 
    "type": "sgv", 
    "glucose": 70
  }, 
  {
    "trend_arrow": "45_DOWN", 
    "display_time": "2016-10-14T15:59:15-07:00", 
    "noise": 1, 
    "system_time": "2016-10-14T22:57:29-07:00", 
    "direction": "FortyFiveDown", 
    "sgv": 74, 
    "dateString": "2016-10-14T15:59:15-07:00", 
    "device": "openaps://indy-e3/cgm", 
    "unfiltered": 80480, 
    "rssi": 172, 
    "date": 1476485955000, 
    "filtered": 87104, 
    "type": "sgv", 
    "glucose": 74
  }
]