[
  {
    "trend_arrow": "FLAT", 
    "display_time": "2016-09-28T07:45:06-07:00", 
    "noise": 1, 
    "direction": "Flat", 
    "system_time": "2016-09-28T14:43:35-07:00", 
    "sgv": 117, 
    "dateString": "2016-09-28T07:45:06-07:00", 
    "device": "openaps://indy-e3/cgm", 
    "unfiltered": 118992, 
    "rssi": 199, 
    "date": 1475073906000.0, 
    "filtered": 114352, 
    "type": "sgv", 
    "glucose": 117
  }, 
  {
    "trend_arrow": "FLAT", 
    "display_time": "2016-09-28T07:40:06-07:00", 
    "noise": 1, 
    "direction": "Flat", 
    "system_time": "2016-09-28T14:38:35-07:00", 
    "sgv": 113, 
    "dateString": "2016-09-28T07:40:06-07:00", 
    "device": "openaps://indy-e3/cgm", 
    "unfiltered": 115984, 
    "rssi": 196, 
    "date": 1475073606000.0, 
    "filtered": 113856, 
    "type": "sgv", 
    "glucose": 113
  }, 
  {
    "trend_arrow": "FLAT", 
    "display_time": "2016-09-28T07:35:06-07:00", 
    "noise": 1, 
    "direction": "Flat", 
    "system_time": "2016-09-28T14:33:36-07:00", 
    "sgv": 109, 
    "dateString": "2016-09-28T07:35:06-07:00", 
    "device": "openaps://indy-e3/cgm", 
    "unfiltered": 113264, 
    "rssi": 196, 
    "date": 1475073306000.0, 
    "filtered": 114864, 
    "type": "sgv", 
    "glucose": 109
  }, 
  {
    "trend_arrow": "FLAT", 
    "display_time": "2016-09-28T07:30:06-07:00", 
    "noise": 1, 
    "direction": "Flat", 
    "system_time": "2016-09-28T14:28:36-07:00", 
    "sgv": 110, 
    "dateString": "2016-09-28T07:30:06-07:00", 
    "device": "openaps://indy-e3/cgm", 
    "unfiltered": 113712, 
    "rssi": 207, 
    "date": 1475073006000.0, 
    "filtered": 116688, 
    "type": "sgv", 
    "glucose": 110
  }, 
  {
    "trend_arrow": "FLAT", 
    "display_time": "2016-09-28T07:25:06-07:00", 
    "noise": 1, 
    "direction": "Flat", 
    "system_time": "2016-09-28T14:23:36-07:00", 
    "sgv": 112, 
    "dateString": "2016-09-28T07:25:06-07:00", 
    "device": "openaps://indy-e3/cgm", 
    "unfiltered": 115536, 
    "rssi": 202, 
    "date": 1475072706000.0, 
    "filtered": 118800, 
    "type": "sgv", 
    "glucose": 112
  }, 
  {
    "trend_arrow": "FLAT", 
    "display_time": "2016-09-28T07:20:06-07:00", 
    "noise": 1, 
    "direction": "Flat", 
    "system_time": "2016-09-28T14:18:36-07:00", 
    "sgv": 116, 
    "dateString": "2016-09-28T07:20:06-07:00", 
    "device": "openaps://indy-e3/cgm", 
    "unfiltered": 118240, 
    "rssi": 203, 
    "date": 1475072406000.0, 
    "filtered": 120800, 
    "type": "sgv", 
    "glucose": 116
  }
]