[
  {
    "trend_arrow": "FLAT", 
    "display_time": "2016-07-24T05:54:11-07:00", 
    "noise": 1, 
    "direction": "Flat", 
    "system_time": "2016-07-24T12:52:58-07:00", 
    "sgv": 136, 
    "dateString": "2016-07-24T05:54:11-07:00", 
    "device": "openaps://cgm", 
    "unfiltered": 161664, 
    "rssi": 194, 
    "date": 1469364851000.0, 
    "filtered": 162240, 
    "type": "sgv", 
    "glucose": 136
  }, 
  {
    "trend_arrow": "FLAT", 
    "display_time": "2016-07-24T05:49:12-07:00", 
    "noise": 1, 
    "direction": "Flat", 
    "system_time": "2016-07-24T12:47:59-07:00", 
    "sgv": 137, 
    "dateString": "2016-07-24T05:49:12-07:00", 
    "device": "openaps://cgm", 
    "unfiltered": 161856, 
    "rssi": 450, 
    "date": 1469364552000.0, 
    "filtered": 164352, 
    "type": "sgv", 
    "glucose": 137
  }, 
  {
    "trend_arrow": "FLAT", 
    "display_time": "2016-07-24T05:44:12-07:00", 
    "noise": 1, 
    "direction": "Flat", 
    "system_time": "2016-07-24T12:42:58-07:00", 
    "sgv": 137, 
    "dateString": "2016-07-24T05:44:12-07:00", 
    "device": "openaps://cgm", 
    "unfiltered": 162592, 
    "rssi": 194, 
    "date": 1469364252000.0, 
    "filtered": 166976, 
    "type": "sgv", 
    "glucose": 137
  }, 
  {
    "trend_arrow": "FLAT", 
    "display_time": "2016-07-24T05:39:12-07:00", 
    "noise": 1, 
    "direction": "Flat", 
    "system_time": "2016-07-24T12:37:58-07:00", 
    "sgv": 140, 
    "dateString": "2016-07-24T05:39:12-07:00", 
    "device": "openaps://cgm", 
    "unfiltered": 164960, 
    "rssi": 192, 
    "date": 1469363952000.0, 
    "filtered": 169280, 
    "type": "sgv", 
    "glucose": 140
  }, 
  {
    "trend_arrow": "FLAT", 
    "display_time": "2016-07-24T05:34:12-07:00", 
    "noise": 1, 
    "direction": "Flat", 
    "system_time": "2016-07-24T12:32:58-07:00", 
    "sgv": 143, 
    "dateString": "2016-07-24T05:34:12-07:00", 
    "device": "openaps://cgm", 
    "unfiltered": 168000, 
    "rssi": 179, 
    "date": 1469363652000.0, 
    "filtered": 170784, 
    "type": "sgv", 
    "glucose": 143
  }, 
  {
    "trend_arrow": "FLAT", 
    "display_time": "2016-07-24T05:29:12-07:00", 
    "noise": 1, 
    "direction": "Flat", 
    "system_time": "2016-07-24T12:27:59-07:00", 
    "sgv": 146, 
    "dateString": "2016-07-24T05:29:12-07:00", 
    "device": "openaps://cgm", 
    "unfiltered": 170624, 
    "rssi": 447, 
    "date": 1469363352000.0, 
    "filtered": 171264, 
    "type": "sgv", 
    "glucose": 146
  }
]