[
  {
    "trend_arrow": "FLAT", 
    "display_time": "2016-11-05T01:36:17-07:00", 
    "noise": 1, 
    "direction": "Flat", 
    "system_time": "2016-11-05T08:35:51-07:00", 
    "sgv": 102, 
    "dateString": "2016-11-05T01:36:17-07:00", 
    "device": "openaps://indy-e3/cgm", 
    "unfiltered": 111024, 
    "rssi": 177, 
    "date": 1478334977000.0, 
    "filtered": 112416, 
    "type": "sgv", 
    "glucose": 102
  }, 
  {
    "trend_arrow": "FLAT", 
    "display_time": "2016-11-05T01:31:17-07:00", 
    "noise": 1, 
    "direction": "Flat", 
    "system_time": "2016-11-05T08:30:51-07:00", 
    "sgv": 104, 
    "dateString": "2016-11-05T01:31:17-07:00", 
    "device": "openaps://indy-e3/cgm", 
    "unfiltered": 112192, 
    "rssi": 173, 
    "date": 1478334677000.0, 
    "filtered": 113712, 
    "type": "sgv", 
    "glucose": 104
  }, 
  {
    "trend_arrow": "FLAT", 
    "display_time": "2016-11-05T01:26:17-07:00", 
    "noise": 1, 
    "direction": "Flat", 
    "system_time": "2016-11-05T08:25:51-07:00", 
    "sgv": 105, 
    "dateString": "2016-11-05T01:26:17-07:00", 
    "device": "openaps://indy-e3/cgm", 
    "unfiltered": 113360, 
    "rssi": 176, 
    "date": 1478334377000.0, 
    "filtered": 115472, 
    "type": "sgv", 
    "glucose": 105
  }, 
  {
    "trend_arrow": "FLAT", 
    "display_time": "2016-11-05T01:21:17-07:00", 
    "noise": 1, 
    "direction": "Flat", 
    "system_time": "2016-11-05T08:20:51-07:00", 
    "sgv": 106, 
    "dateString": "2016-11-05T01:21:17-07:00", 
    "device": "openaps://indy-e3/cgm", 
    "unfiltered": 114256, 
    "rssi": 176, 
    "date": 1478334077000.0, 
    "filtered": 117056, 
    "type": "sgv", 
    "glucose": 106
  }, 
  {
    "trend_arrow": "FLAT", 
    "display_time": "2016-11-05T01:16:17-07:00", 
    "noise": 1, 
    "direction": "Flat", 
    "system_time": "2016-11-05T08:15:51-07:00", 
    "sgv": 107, 
    "dateString": "2016-11-05T01:16:17-07:00", 
    "device": "openaps://indy-e3/cgm", 
    "unfiltered": 114816, 
    "rssi": 176, 
    "date": 1478333777000.0, 
    "filtered": 117840, 
    "type": "sgv", 
    "glucose": 107
  }, 
  {
    "trend_arrow": "FLAT", 
    "display_time": "2016-11-05T01:11:17-07:00", 
    "noise": 1, 
    "direction": "Flat", 
    "system_time": "2016-11-05T08:10:51-07:00", 
    "sgv": 111, 
    "dateString": "2016-11-05T01:11:17-07:00", 
    "device": "openaps://indy-e3/cgm", 
    "unfiltered": 118192, 
    "rssi": 177, 
    "date": 1478333477000.0, 
    "filtered": 117952, 
    "type": "sgv", 
    "glucose": 111
  }
]