[
  {
    "trend_arrow": "FLAT", 
    "display_time": "2016-10-05T13:49:28-07:00", 
    "noise": 1, 
    "system_time": "2016-10-05T20:47:57-07:00", 
    "direction": "Flat", 
    "sgv": 159, 
    "dateString": "2016-10-05T13:49:28-07:00", 
    "device": "openaps://indy-e3/cgm", 
    "unfiltered": 173792, 
    "rssi": 182, 
    "date": 1475700568000, 
    "filtered": 171488, 
    "type": "sgv", 
    "glucose": 159
  }, 
  {
    "trend_arrow": "45_UP", 
    "display_time": "2016-10-05T13:44:28-07:00", 
    "noise": 1, 
    "system_time": "2016-10-05T20:42:58-07:00", 
    "direction": "FortyFiveUp", 
    "sgv": 160, 
    "dateString": "2016-10-05T13:44:28-07:00", 
    "device": "openaps://indy-e3/cgm", 
    "unfiltered": 174144, 
    "rssi": 425, 
    "date": 1475700268000, 
    "filtered": 165664, 
    "type": "sgv", 
    "glucose": 160
  }
]