[
  {
    "trend_arrow": "FLAT", 
    "display_time": "2016-10-22T00:43:48-07:00", 
    "noise": 1, 
    "system_time": "2016-10-22T07:41:33-07:00", 
    "direction": "Flat", 
    "sgv": 119, 
    "dateString": "2016-10-22T00:43:48-07:00", 
    "device": "openaps://indy-e3/cgm", 
    "unfiltered": 114032, 
    "rssi": 188, 
    "date": 1477122228000, 
    "filtered": 111408, 
    "type": "sgv", 
    "glucose": 119
  }, 
  {
    "trend_arrow": "FLAT", 
    "display_time": "2016-10-22T00:38:48-07:00", 
    "noise": 1, 
    "system_time": "2016-10-22T07:36:33-07:00", 
    "direction": "Flat", 
    "sgv": 119, 
    "dateString": "2016-10-22T00:38:48-07:00", 
    "device": "openaps://indy-e3/cgm", 
    "unfiltered": 113504, 
    "rssi": 186, 
    "date": 1477121928000, 
    "filtered": 108448, 
    "type": "sgv", 
    "glucose": 119
  }
]