[
  {
    "trend_arrow": "FLAT", 
    "system_time": "2016-10-14T13:37:30", 
    "noise": 1, 
    "direction": "Flat", 
    "sgv": 131, 
    "display_time": "2016-10-14T06:39:17", 
    "date": 1476452357000.0, 
    "dateString": "2016-10-14T06:39:17", 
    "unfiltered": 133056, 
    "filtered": 134624, 
    "device": "openaps://indy-e3/cgm", 
    "rssi": 194, 
    "type": "sgv", 
    "glucose": 131
  }, 
  {
    "trend_arrow": "FLAT", 
    "system_time": "2016-10-14T13:32:31", 
    "noise": 1, 
    "direction": "Flat", 
    "sgv": 133, 
    "display_time": "2016-10-14T06:34:18", 
    "date": 1476452058000.0, 
    "dateString": "2016-10-14T06:34:18", 
    "unfiltered": 135072, 
    "filtered": 134272, 
    "device": "openaps://indy-e3/cgm", 
    "rssi": 443, 
    "type": "sgv", 
    "glucose": 133
  }, 
  {
    "trend_arrow": "FLAT", 
    "system_time": "2016-10-14T13:32:31", 
    "noise": 1, 
    "direction": "Flat", 
    "sgv": 133, 
    "display_time": "2016-10-14T06:34:18", 
    "date": 1476452058000.0, 
    "dateString": "2016-10-14T06:34:18", 
    "unfiltered": 135808, 
    "filtered": 133888, 
    "device": "openaps://indy-e3/cgm", 
    "rssi": 186, 
    "type": "sgv", 
    "glucose": 133
  }, 
  {
    "trend_arrow": "FLAT", 
    "system_time": "2016-10-14T13:27:30", 
    "noise": 1, 
    "direction": "Flat", 
    "sgv": 134, 
    "display_time": "2016-10-14T06:29:17", 
    "date": 1476451757000.0, 
    "dateString": "2016-10-14T06:29:17", 
    "unfiltered": 133280, 
    "filtered": 133760, 
    "device": "openaps://indy-e3/cgm", 
    "rssi": 441, 
    "type": "sgv", 
    "glucose": 134
  }, 
  {
    "trend_arrow": "FLAT", 
    "system_time": "2016-10-14T13:22:31", 
    "noise": 1, 
    "direction": "Flat", 
    "sgv": 130, 
    "display_time": "2016-10-14T06:24:17", 
    "date": 1476451457000.0, 
    "dateString": "2016-10-14T06:24:17", 
    "unfiltered": 133760, 
    "filtered": 133696, 
    "device": "openaps://indy-e3/cgm", 
    "rssi": 186, 
    "type": "sgv", 
    "glucose": 130
  }, 
  {
    "trend_arrow": "FLAT", 
    "system_time": "2016-10-14T13:17:30", 
    "noise": 1, 
    "direction": "Flat", 
    "sgv": 131, 
    "display_time": "2016-10-14T06:19:17", 
    "date": 1476451157000.0, 
    "dateString": "2016-10-14T06:19:17", 
    "unfiltered": 133760, 
    "filtered": 133536, 
    "device": "openaps://indy-e3/cgm", 
    "rssi": 435, 
    "type": "sgv", 
    "glucose": 131
  }, 
  {
    "trend_arrow": "FLAT", 
    "system_time": "2016-10-14T13:12:31", 
    "noise": 1, 
    "direction": "Flat", 
    "sgv": 131, 
    "display_time": "2016-10-14T06:14:17", 
    "date": 1476450857000.0, 
    "dateString": "2016-10-14T06:14:17", 
    "device": "openaps://indy-e3/cgm", 
    "type": "sgv", 
    "glucose": 131
  }
]